[{"date":"3/28（金）","match":{"home":"巨人","visitor":"ヤクルト"},"info":{"place":"東京ドーム","time":"18:15"},"comment":"","pit":["勝：マルティネス","敗：清水"]},{"date":"3/28（金）","match":{"home":"DeNA","visitor":"中日"},"info":{"place":"横浜","time":"18:30"},"comment":"","pit":["勝：東","敗：髙橋宏"]},{"date":"3/28（金）","match":{"home":"広島","visitor":"阪神"},"info":{"place":"マツダスタジアム","time":"18:00"},"comment":"","pit":["勝：村上","敗：森下"]},{"date":"3/28（金）","match":{"home":"西武","visitor":"日本ハム"},"info":{"place":"ベルーナドーム","time":"18:00"},"comment":"","pit":["勝：金村","敗：今井"]},{"date":"3/28（金）","match":{"home":"オリックス","visitor":"楽天"},"info":{"place":"京セラD大阪","time":"18:30"},"comment":"","pit":["勝：マチャド","敗：鈴木翔"]},{"date":"3/28（金）","match":{"home":"ソフトバンク","visitor":"ロッテ"},"info":{"place":"みずほPayPay","time":"18:30"},"comment":"","pit":["勝：中森","敗：有原"]},{"date":"3/29（土）","match":{"home":"巨人","visitor":"ヤクルト"},"info":{"place":"東京ドーム","time":"14:00"},"comment":"","pit":["勝：赤星","敗：吉村"]},{"date":"3/29（土）","match":{"home":"DeNA","visitor":"中日"},"info":{"place":"横浜","time":"14:00"},"comment":"","pit":["勝：松葉","敗：バウアー"]},{"date":"3/29（土）","match":{"home":"広島","visitor":"阪神"},"info":{"place":"マツダスタジアム","time":"14:00"},"comment":"","pit":["勝：及川","敗：床田"]},{"date":"3/29（土）","match":{"home":"西武","visitor":"日本ハム"},"info":{"place":"ベルーナドーム","time":"14:00"},"comment":"","pit":["勝：福谷","敗：ウィンゲンター"]},{"date":"3/29（土）","match":{"home":"オリックス","visitor":"楽天"},"info":{"place":"京セラD大阪","time":"14:00"},"comment":"","pit":["勝：則本","敗：山田"]},{"date":"3/29（土）","match":{"home":"ソフトバンク","visitor":"ロッテ"},"info":{"place":"みずほPayPay","time":"14:00"},"comment":"","pit":["勝：ゲレーロ","敗：藤井"]},{"date":"3/30（日）","match":{"home":"巨人","visitor":"ヤクルト"},"info":{"place":"東京ドーム","time":"14:00"},"comment":"","pit":["勝：石川","敗：高橋"]},{"date":"3/30（日）","match":{"home":"DeNA","visitor":"中日"},"info":{"place":"横浜","time":"14:00"},"comment":"","pit":["勝：平良","敗：メヒア"]},{"date":"3/30（日）","match":{"home":"広島","visitor":"阪神"},"info":{"place":"マツダスタジアム","time":"13:30"},"comment":"","pit":["勝：森","敗：門別"]},{"date":"3/30（日）","match":{"home":"西武","visitor":"日本ハム"},"info":{"place":"ベルーナドーム","time":"13:00"},"comment":"","pit":["勝：バーヘイゲン","敗：髙橋光成"]},{"date":"3/30（日）","match":{"home":"オリックス","visitor":"楽天"},"info":{"place":"京セラD大阪","time":"13:00"},"comment":"","pit":["勝：髙島","敗：辛島"]},{"date":"3/30（日）","match":{"home":"ソフトバンク","visitor":"ロッテ"},"info":{"place":"みずほPayPay","time":"13:00"},"comment":"","pit":["勝：木村","敗：杉山"]}]